setup.cfg
setup.py
tests/__init__.py
tests/test_widget.py
toscawidgets/__init__.py
toscawidgets/widgets/__init__.py
toscawidgets/widgets/maps/__init__.py
toscawidgets/widgets/maps/gmap.py
toscawidgets/widgets/maps/release.py
toscawidgets/widgets/maps/samples.py
toscawidgets/widgets/maps/widgets.py
toscawidgets/widgets/maps/static/gmap/gmap.css
toscawidgets/widgets/maps/static/gmap/gmap.js
toscawidgets/widgets/maps/static/map/map.js
twMaps.egg-info/PKG-INFO
twMaps.egg-info/SOURCES.txt
twMaps.egg-info/dependency_links.txt
twMaps.egg-info/entry_points.txt
twMaps.egg-info/namespace_packages.txt
twMaps.egg-info/not-zip-safe
twMaps.egg-info/paster_plugins.txt
twMaps.egg-info/requires.txt
twMaps.egg-info/top_level.txt
twMapsSampleAppPylons/README.txt
twMapsSampleAppPylons/development.ini
twMapsSampleAppPylons/setup.cfg
twMapsSampleAppPylons/setup.py
twMapsSampleAppPylons/test.ini
twMapsSampleAppPylons/ez_setup/README.txt
twMapsSampleAppPylons/ez_setup/__init__.py
twMapsSampleAppPylons/twMapsSampleAppPylons.egg-info/paste_deploy_config.ini_tmpl
twMapsSampleAppPylons/twMapsSampleAppPylons.egg-info/paster_plugins.txt
twMapsSampleAppPylons/twmapssampleapppylons/__init__.py
twMapsSampleAppPylons/twmapssampleapppylons/websetup.py
twMapsSampleAppPylons/twmapssampleapppylons/config/__init__.py
twMapsSampleAppPylons/twmapssampleapppylons/config/environment.py
twMapsSampleAppPylons/twmapssampleapppylons/config/middleware.py
twMapsSampleAppPylons/twmapssampleapppylons/config/routing.py
twMapsSampleAppPylons/twmapssampleapppylons/controllers/__init__.py
twMapsSampleAppPylons/twmapssampleapppylons/controllers/error.py
twMapsSampleAppPylons/twmapssampleapppylons/controllers/maps.py
twMapsSampleAppPylons/twmapssampleapppylons/controllers/template.py
twMapsSampleAppPylons/twmapssampleapppylons/docs/index.txt
twMapsSampleAppPylons/twmapssampleapppylons/i18n/__init__.py
twMapsSampleAppPylons/twmapssampleapppylons/lib/__init__.py
twMapsSampleAppPylons/twmapssampleapppylons/lib/app_globals.py
twMapsSampleAppPylons/twmapssampleapppylons/lib/base.py
twMapsSampleAppPylons/twmapssampleapppylons/lib/helpers.py
twMapsSampleAppPylons/twmapssampleapppylons/models/__init__.py
twMapsSampleAppPylons/twmapssampleapppylons/templates/layout.html
twMapsSampleAppPylons/twmapssampleapppylons/templates/map.html
twMapsSampleAppPylons/twmapssampleapppylons/tests/__init__.py
twMapsSampleAppPylons/twmapssampleapppylons/tests/test_models.py
