Metadata-Version: 1.0
Name: twMaps
Version: 0.1a0.dev-r720
Summary: Web map widgets
Home-page: http://wyattbaldwin.com/
Author: Wyatt Baldwin, byCycle.org
Author-email: wyatt@bycycle.org
License: UNKNOWN
Keywords: web maps google widgets toscawidgets toscawidgets.widgets
Platform: UNKNOWN
Classifier: Development Status :: 3 - Alpha
Classifier: Environment :: Web Environment
Classifier: Framework :: Paste
Classifier: Intended Audience :: Developers
Classifier: License :: OSI Approved :: BSD License
Classifier: License :: OSI Approved :: MIT License
Classifier: Natural Language :: English
Classifier: Programming Language :: Python
Classifier: Topic :: Scientific/Engineering :: GIS
